{"metric": -1.848031951121104, "time_this_iter_s": 0.0, "done": false, "timesteps_total": null, "episodes_total": null, "training_iteration": 1, "trial_id": "542d9110", "experiment_id": "9c64ed2a638e425c931278fa2c59490a", "date": "2022-10-27_18-49-10", "timestamp": 1666918150, "time_total_s": 0.0, "pid": 29244, "hostname": "Lil_machine2", "node_ip": "127.0.0.1", "config": {"x": 1.848031951121104}, "time_since_restore": 0.0, "timesteps_since_restore": 0, "iterations_since_restore": 1, "warmup_time": 0.00798177719116211}
